lambda_kinesis/__init__.py
lambda_kinesis/runner.py
local_lambda_kinesis-0.0.2.data/scripts/lambda_kinesis
tests/__init__.py
tests/unit_tests/__init__.py
tests/unit_tests/test_runner.py
local_lambda_kinesis-0.0.2.dist-info/METADATA
local_lambda_kinesis-0.0.2.dist-info/WHEEL
local_lambda_kinesis-0.0.2.dist-info/top_level.txt
local_lambda_kinesis-0.0.2.dist-info/RECORD
