Metadata-Version: 2.1
Name: local-lambda-kinesis
Version: 0.0.2
Summary: Tool for testing lambda kinesis handlers locally using real data
Home-page: https://github.com/kobybum/local-lambda-kinesis
Author: Koby Bass
License: UNKNOWN
Platform: UNKNOWN
Requires-Python: >=3.6
Requires-Dist: boto3 (>=1.9.236)
